cli.py
leapcli/__init__.py
leapcli/dataset.py
leapcli/doctor.py
leapcli/enums.py
leapcli/exceptions.py
leapcli/get.py
leapcli/log.py
leapcli/login.py
leapcli/mapping/leap_graph_editor.py
leapcli/project.py
leapcli/push.py
templates/.tensorleap/config.toml
templates/.tensorleap/dataset.py
templates/.tensorleap/model.py
leapcli-0.2.36.dist-info/entry_points.txt
leapcli-0.2.36.dist-info/LICENSE
leapcli-0.2.36.dist-info/WHEEL
leapcli-0.2.36.dist-info/METADATA
leapcli-0.2.36.dist-info/RECORD
