Metadata-Version: 2.1
Name: leapcli
Version: 0.2.36
Summary: Tensorleap CLI
Home-page: https://github.com/tensorleap/cli
License: MIT
Author: Assaf Lavie
Author-email: assaf.lavie@tensorleap.ai
Requires-Python: >=3.8,<3.10
Classifier: License :: OSI Approved :: MIT License
Classifier: Programming Language :: Python :: 3
Classifier: Programming Language :: Python :: 3.8
Classifier: Programming Language :: Python :: 3.9
Requires-Dist: GitPython (>=3.1.27,<4.0.0)
Requires-Dist: code-loader (==0.2.47)
Requires-Dist: docopt (>=0.6.2,<0.7.0)
Requires-Dist: leap-model-parser (==0.1.72)
Requires-Dist: luddite (>=1.0.2,<2.0.0)
Requires-Dist: prettytable (>=3.2.0,<4.0.0)
Requires-Dist: python-json-logger (>=2.0.2,<3.0.0)
Requires-Dist: requests (>=2.27.1,<3.0.0)
Requires-Dist: semver (>=2.13.0,<3.0.0)
Requires-Dist: tensorleap-openapi-client (==1.2.0)
Requires-Dist: toml (>=0.10.2,<0.11.0)
Project-URL: Repository, https://github.com/tensorleap/cli
